cis_checks_2023/__init__.py
cis_checks_2023/_security_control_5.py
cis_checks_2023/iam_control_1.py
cis_checks_2023/logging_control_3.py
cis_checks_2023/monitoring_control_4.py
cis_checks_2023/networking_control_5.py
cis_checks_2023/storage_control_2.py
cis_checks_2023/utils.py
cis_checks_2023-2.1.0.dist-info/METADATA
cis_checks_2023-2.1.0.dist-info/WHEEL
cis_checks_2023-2.1.0.dist-info/top_level.txt
cis_checks_2023-2.1.0.dist-info/RECORD
